[
  {
    "_objectives": [
      {
        "_type": "s",
        "_material": "Wagon",
        "_neededAmount": 400,
        "_currentAmount": 0,
        "_initialAmount": 0
      }
    ],
    "_number": 10,
    "_contractor": "Mizuki",
    "_description": "",
    "_selected": false,
    "_any": false
  },
  {
    "_objectives": [
      {
        "_type": "b",
        "_material": "Wood",
        "_neededAmount": 90000,
        "_currentAmount": 0,
        "_initialAmount": 0
      },
      {
        "_type": "b",
        "_material": "Nails",
        "_neededAmount": 25000,
        "_currentAmount": 0,
        "_initialAmount": 0
      }
    ],
    "_number": 4,
    "_contractor": "Mizuki",
    "_selected": false,
    "_any": false
  },
  {
    "_objectives": [
      {
        "_type": "b",
        "_material": "Glass",
        "_neededAmount": 90000,
        "_currentAmount": 0,
        "_initialAmount": 0
      },
      {
        "_type": "b",
        "_material": "Steel",
        "_neededAmount": 90000,
        "_currentAmount": 0,
        "_initialAmount": 0
      },
      {
        "_type": "b",
        "_material": "Cement",
        "_neededAmount": 45000,
        "_currentAmount": 0,
        "_initialAmount": 0
      }
    ],
    "_number": 5,
    "_contractor": "Mizuki",
    "_selected": false,
    "_any": false
  },
  {
    "_objectives": [
      {
        "_type": "d",
        "_material": "Gold",
        "_neededAmount": 1575000,
        "_currentAmount": 0,
        "_initialAmount": 0
      }
    ],
    "_number": 6,
    "_contractor": "Mizuki",
    "_selected": false,
    "_any": false
  },
  {
    "_objectives": [
      {
        "_type": "d",
        "_material": "Carbon",
        "_neededAmount": 80000,
        "_currentAmount": 0,
        "_initialAmount": 0
      },
      {
        "_type": "d",
        "_material": "Titanium",
        "_neededAmount": 55000,
        "_currentAmount": 0,
        "_initialAmount": 0
      },
      {
        "_type": "d",
        "_material": "Marble",
        "_neededAmount": 45000,
        "_currentAmount": 0,
        "_initialAmount": 0
      }
    ],
    "_number": 7,
    "_contractor": "Mizuki",
    "_selected": false,
    "_any": false
  },
  {
    "_objectives": [
      {
        "_type": "s",
        "_material": "Loco",
        "_neededAmount": 25,
        "_currentAmount": 0,
        "_initialAmount": 0
      }
    ],
    "_number": 8,
    "_contractor": "Mizuki",
    "_selected": false,
    "_any": false
  },
  {
    "_objectives": [
      {
        "_type": "s",
        "_material": "Loco",
        "_neededAmount": 25,
        "_currentAmount": 0,
        "_initialAmount": 0
      }
    ],
    "_number": 9,
    "_contractor": "Mizuki",
    "_selected": false,
    "_any": false
  },
  {
    "_objectives": [
      {
        "_type": "s",
        "_material": "Wagon",
        "_neededAmount": 400,
        "_currentAmount": 0,
        "_initialAmount": 0
      }
    ],
    "_number": 10,
    "_contractor": "Mizuki",
    "_selected": false,
    "_any": false
  },
  {
    "_objectives": [
      {
        "_type": "s",
        "_material": "TS",
        "_neededAmount": 35,
        "_currentAmount": 0,
        "_initialAmount": 0
      }
    ],
    "_number": 11,
    "_contractor": "Mizuki",
    "_selected": false,
    "_any": false
  },
  {
    "_objectives": [
      {
        "_type": "s",
        "_material": "TS",
        "_neededAmount": 35,
        "_currentAmount": 0,
        "_initialAmount": 0
      }
    ],
    "_number": 12,
    "_contractor": "Mizuki",
    "_selected": false,
    "_any": false
  },
  {
    "_objectives": [
      {
        "_type": "d",
        "_material": "Gold",
        "_neededAmount": 2850000,
        "_currentAmount": 0,
        "_initialAmount": 0
      }
    ],
    "_number": 13,
    "_contractor": "Mizuki",
    "_selected": false,
    "_any": false
  },
  {
    "_objectives": [
      {
        "_type": "b",
        "_material": "Gold",
        "_neededAmount": 860000,
        "_currentAmount": 0,
        "_initialAmount": 0
      },
      {
        "_type": "b",
        "_material": "Fuel",
        "_neededAmount": 93500,
        "_currentAmount": 0,
        "_initialAmount": 0
      }
    ],
    "_number": 14,
    "_contractor": "Mizuki",
    "_selected": false,
    "_any": false
  },
  {
    "_objectives": [
      {
        "_type": "d",
        "_material": "Nails",
        "_neededAmount": 70000,
        "_currentAmount": 0,
        "_initialAmount": 0
      },
      {
        "_type": "d",
        "_material": "Bricks",
        "_neededAmount": 65000,
        "_currentAmount": 0,
        "_initialAmount": 0
      },
      {
        "_type": "d",
        "_material": "Steel",
        "_neededAmount": 60000,
        "_currentAmount": 0,
        "_initialAmount": 0
      }
    ],
    "_number": 15,
    "_contractor": "Mizuki",
    "_selected": false,
    "_any": false
  },
  {
    "_objectives": [
      {
        "_type": "d",
        "_material": "Gold",
        "_neededAmount": 3950000,
        "_currentAmount": 0,
        "_initialAmount": 0
      }
    ],
    "_number": 16,
    "_contractor": "Mizuki",
    "_selected": false,
    "_any": false
  },
  {
    "_objectives": [
      {
        "_type": "s",
        "_material": "Wagon",
        "_neededAmount": 50,
        "_currentAmount": 0,
        "_initialAmount": 0
      }
    ],
    "_number": 17,
    "_contractor": "Mizuki",
    "_selected": false,
    "_any": false
  },
  {
    "_objectives": [
      {
        "_type": "b",
        "_material": "Gold",
        "_neededAmount": 4500000,
        "_currentAmount": 0,
        "_initialAmount": 0
      },
      {
        "_type": "b",
        "_material": "Steel",
        "_neededAmount": 100000,
        "_currentAmount": 0,
        "_initialAmount": 0
      },
      {
        "_type": "b",
        "_material": "Gravel",
        "_neededAmount": 100000,
        "_currentAmount": 0,
        "_initialAmount": 0
      }
    ],
    "_number": 18,
    "_contractor": "Mizuki",
    "_selected": false,
    "_any": false
  },
  {
    "_objectives": [
      {
        "_type": "d",
        "_material": "Gold",
        "_neededAmount": 4680000,
        "_currentAmount": 0,
        "_initialAmount": 0
      },
      {
        "_type": "d",
        "_material": "Wood",
        "_neededAmount": 75000,
        "_currentAmount": 0,
        "_initialAmount": 0
      },
      {
        "_type": "d",
        "_material": "Nails",
        "_neededAmount": 75000,
        "_currentAmount": 0,
        "_initialAmount": 0
      }
    ],
    "_number": 19,
    "_contractor": "Mizuki",
    "_selected": false,
    "_any": false
  },
  {
    "_objectives": [
      {
        "_type": "d",
        "_material": "Gold",
        "_neededAmount": 5500000,
        "_currentAmount": 0,
        "_initialAmount": 0
      }
    ],
    "_number": 20,
    "_contractor": "Mizuki",
    "_selected": false,
    "_any": false
  },
  {
    "_objectives": [
      {
        "_type": "d",
        "_material": "Wood",
        "_neededAmount": 100000,
        "_currentAmount": 0,
        "_initialAmount": 0
      },
      {
        "_type": "d",
        "_material": "Nails",
        "_neededAmount": 100000,
        "_currentAmount": 0,
        "_initialAmount": 0
      }
    ],
    "_number": 21,
    "_contractor": "Mizuki",
    "_selected": false,
    "_any": false
  },
  {
    "_objectives": [
      {
        "_type": "s",
        "_material": "Loco",
        "_neededAmount": 35,
        "_currentAmount": 0,
        "_initialAmount": 0
      }
    ],
    "_number": 22,
    "_contractor": "Mizuki",
    "_selected": false,
    "_any": false
  },
  {
    "_objectives": [
      {
        "_type": "d",
        "_material": "Gold",
        "_neededAmount": 5920000,
        "_currentAmount": 0,
        "_initialAmount": 0
      },
      {
        "_type": "d",
        "_material": "Wood",
        "_neededAmount": 85000,
        "_currentAmount": 0,
        "_initialAmount": 0
      },
      {
        "_type": "d",
        "_material": "Glass",
        "_neededAmount": 85000,
        "_currentAmount": 0,
        "_initialAmount": 0
      }
    ],
    "_number": 23,
    "_contractor": "Mizuki",
    "_selected": false,
    "_any": false
  },
  {
    "_objectives": [
      {
        "_type": "s",
        "_material": "Wagon",
        "_neededAmount": 300,
        "_currentAmount": 0,
        "_initialAmount": 0
      }
    ],
    "_number": 24,
    "_contractor": "Mizuki",
    "_selected": false,
    "_any": false
  },
  {
    "_objectives": [
      {
        "_type": "s",
        "_material": "TS",
        "_neededAmount": 45,
        "_currentAmount": 0,
        "_initialAmount": 0
      }
    ],
    "_number": 25,
    "_contractor": "Mizuki",
    "_selected": false,
    "_any": false
  },
  {
    "_objectives": [
      {
        "_type": "d",
        "_material": "Gold",
        "_neededAmount": 5920000,
        "_currentAmount": 0,
        "_initialAmount": 0
      },
      {
        "_type": "d",
        "_material": "Nails",
        "_neededAmount": 85000,
        "_currentAmount": 0,
        "_initialAmount": 0
      },
      {
        "_type": "d",
        "_material": "Glass",
        "_neededAmount": 85000,
        "_currentAmount": 0,
        "_initialAmount": 0
      }
    ],
    "_number": 26,
    "_contractor": "Mizuki",
    "_selected": false,
    "_any": false
  },
  {
    "_objectives": [
      {
        "_type": "s",
        "_material": "TS",
        "_neededAmount": 45,
        "_currentAmount": 0,
        "_initialAmount": 0
      }
    ],
    "_number": 27,
    "_contractor": "Mizuki",
    "_selected": false,
    "_any": false
  },
  {
    "_objectives": [
      {
        "_type": "b",
        "_material": "Gravel",
        "_neededAmount": 300000,
        "_currentAmount": 0,
        "_initialAmount": 0
      },
      {
        "_type": "b",
        "_material": "Carbon",
        "_neededAmount": 180000,
        "_currentAmount": 0,
        "_initialAmount": 0
      },
      {
        "_type": "b",
        "_material": "Wires",
        "_neededAmount": 140000,
        "_currentAmount": 0,
        "_initialAmount": 0
      }
    ],
    "_number": 28,
    "_contractor": "Mizuki",
    "_selected": false,
    "_any": false
  },
  {
    "_objectives": [
      {
        "_type": "b",
        "_material": "Fuel",
        "_neededAmount": 300000,
        "_currentAmount": 0,
        "_initialAmount": 0
      },
      {
        "_type": "b",
        "_material": "Titanium",
        "_neededAmount": 220000,
        "_currentAmount": 0,
        "_initialAmount": 0
      },
      {
        "_type": "b",
        "_material": "Marble",
        "_neededAmount": 170000,
        "_currentAmount": 0,
        "_initialAmount": 0
      }
    ],
    "_number": 29,
    "_contractor": "Mizuki",
    "_selected": false,
    "_any": false
  },
  {
    "_objectives": [
      {
        "_type": "d",
        "_material": "Gold",
        "_neededAmount": 15300000,
        "_currentAmount": 0,
        "_initialAmount": 0
      }
    ],
    "_number": 30,
    "_contractor": "Mizuki",
    "_selected": false,
    "_any": false
  },
  {
    "_objectives": [
      {
        "_type": "d",
        "_material": "Gold",
        "_neededAmount": 12500000,
        "_currentAmount": 0,
        "_initialAmount": 0
      }
    ],
    "_number": 31,
    "_contractor": "Mizuki",
    "_selected": false,
    "_any": false
  },
  {
    "_objectives": [
      {
        "_type": "d",
        "_material": "Steel",
        "_neededAmount": 160000,
        "_currentAmount": 0,
        "_initialAmount": 0
      },
      {
        "_type": "d",
        "_material": "Wires",
        "_neededAmount": 160000,
        "_currentAmount": 0,
        "_initialAmount": 0
      }
    ],
    "_number": 32,
    "_contractor": "Mizuki",
    "_selected": false,
    "_any": false
  },
  {
    "_objectives": [
      {
        "_type": "s",
        "_material": "Wagon",
        "_neededAmount": 200,
        "_currentAmount": 0,
        "_initialAmount": 0
      }
    ],
    "_number": 33,
    "_contractor": "Mizuki",
    "_selected": false,
    "_any": false
  },
  {
    "_objectives": [
      {
        "_type": "d",
        "_material": "Bricks",
        "_neededAmount": 200000,
        "_currentAmount": 0,
        "_initialAmount": 0
      },
      {
        "_type": "d",
        "_material": "Cement",
        "_neededAmount": 150000,
        "_currentAmount": 0,
        "_initialAmount": 0
      },
      {
        "_type": "d",
        "_material": "Plastics",
        "_neededAmount": 100000,
        "_currentAmount": 0,
        "_initialAmount": 0
      }
    ],
    "_number": 34,
    "_contractor": "Mizuki",
    "_selected": false,
    "_any": false
  },
  {
    "_objectives": [
      {
        "_type": "d",
        "_material": "Gold",
        "_neededAmount": 18000000,
        "_currentAmount": 0,
        "_initialAmount": 0
      }
    ],
    "_number": 35,
    "_contractor": "Mizuki",
    "_selected": false,
    "_any": false
  },
  {
    "_objectives": [
      {
        "_type": "d",
        "_material": "Glass",
        "_neededAmount": 200000,
        "_currentAmount": 0,
        "_initialAmount": 0
      },
      {
        "_type": "d",
        "_material": "Gravel",
        "_neededAmount": 200000,
        "_currentAmount": 0,
        "_initialAmount": 0
      },
      {
        "_type": "d",
        "_material": "Titanium",
        "_neededAmount": 150000,
        "_currentAmount": 0,
        "_initialAmount": 0
      }
    ],
    "_number": 36,
    "_contractor": "Mizuki",
    "_selected": false,
    "_any": false
  },
  {
    "_objectives": [
      {
        "_type": "s",
        "_material": "Maglev",
        "_neededAmount": 45,
        "_currentAmount": 0,
        "_initialAmount": 0
      }
    ],
    "_number": 37,
    "_contractor": "Mizuki",
    "_selected": false,
    "_any": false
  },
  {
    "_objectives": [
      {
        "_type": "s",
        "_material": "Wagon",
        "_neededAmount": 600,
        "_currentAmount": 0,
        "_initialAmount": 0
      },
      {
        "_type": "d",
        "_material": "Wires",
        "_neededAmount": 226800,
        "_currentAmount": 0,
        "_initialAmount": 0
      }
    ],
    "_number": 38,
    "_contractor": "Mizuki",
    "_selected": false,
    "_any": false
  },
  {
    "_objectives": [
      {
        "_type": "d",
        "_material": "Marble",
        "_neededAmount": 250000,
        "_currentAmount": 0,
        "_initialAmount": 0
      }
    ],
    "_number": 39,
    "_contractor": "Mizuki",
    "_selected": false,
    "_any": false
  },
  {
    "_objectives": [
      {
        "_type": "b",
        "_material": "Gold",
        "_neededAmount": 16480000,
        "_currentAmount": 0,
        "_initialAmount": 0
      },
      {
        "_type": "b",
        "_material": "Rubber",
        "_neededAmount": 320000,
        "_currentAmount": 0,
        "_initialAmount": 0
      },
      {
        "_type": "b",
        "_material": "Plastics",
        "_neededAmount": 320000,
        "_currentAmount": 0,
        "_initialAmount": 0
      }
    ],
    "_number": 40,
    "_contractor": "Mizuki",
    "_selected": false,
    "_any": false
  },
  {
    "_objectives": [
      {
        "_type": "d",
        "_material": "Gold",
        "_neededAmount": 23000000,
        "_currentAmount": 0,
        "_initialAmount": 0
      }
    ],
    "_number": 41,
    "_contractor": "Mizuki",
    "_selected": false,
    "_any": false
  },
  {
    "_objectives": [
      {
        "_type": "b",
        "_material": "Gold",
        "_neededAmount": 14480000,
        "_currentAmount": 0,
        "_initialAmount": 0
      },
      {
        "_type": "b",
        "_material": "Bricks",
        "_neededAmount": 440000,
        "_currentAmount": 0,
        "_initialAmount": 0
      },
      {
        "_type": "b",
        "_material": "Silicon",
        "_neededAmount": 320000,
        "_currentAmount": 0,
        "_initialAmount": 0
      }
    ],
    "_number": 42,
    "_contractor": "Mizuki",
    "_selected": false,
    "_any": false
  },
  {
    "_objectives": [
      {
        "_type": "d",
        "_material": "Glass",
        "_neededAmount": 175000,
        "_currentAmount": 0,
        "_initialAmount": 0
      },
      {
        "_type": "d",
        "_material": "Carbon",
        "_neededAmount": 175000,
        "_currentAmount": 0,
        "_initialAmount": 0
      },
      {
        "_type": "d",
        "_material": "Wires",
        "_neededAmount": 175000,
        "_currentAmount": 0,
        "_initialAmount": 0
      }
    ],
    "_number": 43,
    "_contractor": "Mizuki",
    "_selected": false,
    "_any": false
  },
  {
    "_objectives": [
      {
        "_type": "b",
        "_material": "Gold",
        "_neededAmount": 15400000,
        "_currentAmount": 0,
        "_initialAmount": 0
      },
      {
        "_type": "b",
        "_material": "Fuel",
        "_neededAmount": 200000,
        "_currentAmount": 0,
        "_initialAmount": 0
      }
    ],
    "_number": 44,
    "_contractor": "Mizuki",
    "_selected": false,
    "_any": false
  },
  {
    "_objectives": [
      {
        "_type": "d",
        "_material": "Gold",
        "_neededAmount": 5000000,
        "_currentAmount": 0,
        "_initialAmount": 0
      },
      {
        "_type": "d",
        "_material": "Gravel",
        "_neededAmount": 325000,
        "_currentAmount": 0,
        "_initialAmount": 0
      }
    ],
    "_number": 45,
    "_contractor": "Mizuki",
    "_selected": false,
    "_any": false
  },
  {
    "_objectives": [
      {
        "_type": "d",
        "_material": "Gold",
        "_neededAmount": 5000000,
        "_currentAmount": 0,
        "_initialAmount": 0
      },
      {
        "_type": "d",
        "_material": "Marble",
        "_neededAmount": 275000,
        "_currentAmount": 0,
        "_initialAmount": 0
      }
    ],
    "_number": 46,
    "_contractor": "Mizuki",
    "_selected": false,
    "_any": false
  },
  {
    "_objectives": [
      {
        "_type": "s",
        "_material": "TS",
        "_neededAmount": 85,
        "_currentAmount": 0,
        "_initialAmount": 0
      }
    ],
    "_number": 47,
    "_contractor": "Mizuki",
    "_selected": false,
    "_any": false
  },
  {
    "_objectives": [
      {
        "_type": "s",
        "_material": "TS",
        "_neededAmount": 45,
        "_currentAmount": 0,
        "_initialAmount": 0
      }
    ],
    "_number": 48,
    "_contractor": "Mizuki",
    "_selected": false,
    "_any": false
  },
  {
    "_objectives": [
      {
        "_type": "s",
        "_material": "TS",
        "_neededAmount": 30,
        "_currentAmount": 0,
        "_initialAmount": 0
      }
    ],
    "_number": 49,
    "_contractor": "Mizuki",
    "_selected": false,
    "_any": false
  },
  {
    "_objectives": [
      {
        "_type": "d",
        "_material": "Gold",
        "_neededAmount": 19500000,
        "_currentAmount": 0,
        "_initialAmount": 0
      },
      {
        "_type": "d",
        "_material": "Carbon",
        "_neededAmount": 200000,
        "_currentAmount": 0,
        "_initialAmount": 0
      }
    ],
    "_number": 50,
    "_contractor": "Mizuki",
    "_selected": false,
    "_any": false
  },
  {
    "_objectives": [
      {
        "_type": "d",
        "_material": "Gold",
        "_neededAmount": 19500000,
        "_currentAmount": 0,
        "_initialAmount": 0
      },
      {
        "_type": "d",
        "_material": "Titanium",
        "_neededAmount": 200000,
        "_currentAmount": 0,
        "_initialAmount": 0
      }
    ],
    "_number": 51,
    "_contractor": "Mizuki",
    "_selected": false,
    "_any": false
  },
  {
    "_objectives": [
      {
        "_type": "d",
        "_material": "Wires",
        "_neededAmount": 235000,
        "_currentAmount": 0,
        "_initialAmount": 0
      },
      {
        "_type": "d",
        "_material": "Silicon",
        "_neededAmount": 235000,
        "_currentAmount": 0,
        "_initialAmount": 0
      }
    ],
    "_number": 52,
    "_contractor": "Mizuki",
    "_selected": false,
    "_any": false
  },
  {
    "_objectives": [
      {
        "_type": "s",
        "_material": "TS",
        "_neededAmount": 35,
        "_currentAmount": 0,
        "_initialAmount": 0
      }
    ],
    "_number": 53,
    "_contractor": "Mizuki",
    "_selected": false,
    "_any": false
  },
  {
    "_objectives": [
      {
        "_type": "s",
        "_material": "TSany",
        "_neededAmount": 125,
        "_currentAmount": 0,
        "_initialAmount": 0
      }
    ],
    "_number": 54,
    "_contractor": "Mizuki",
    "_selected": false,
    "_any": false
  },
  {
    "_objectives": [
      {
        "_type": "s",
        "_material": "Loco",
        "_neededAmount": 180,
        "_currentAmount": 0,
        "_initialAmount": 0
      }
    ],
    "_number": 55,
    "_contractor": "Mizuki",
    "_selected": false,
    "_any": false
  },
  {
    "_objectives": [
      {
        "_type": "d",
        "_material": "Wood",
        "_neededAmount": 200000,
        "_currentAmount": 0,
        "_initialAmount": 0
      },
      {
        "_type": "d",
        "_material": "Nails",
        "_neededAmount": 200000,
        "_currentAmount": 0,
        "_initialAmount": 0
      },
      {
        "_type": "d",
        "_material": "Steel",
        "_neededAmount": 200000,
        "_currentAmount": 0,
        "_initialAmount": 0
      }
    ],
    "_number": 56,
    "_contractor": "Mizuki",
    "_selected": false,
    "_any": false
  },
  {
    "_objectives": [
      {
        "_type": "b",
        "_material": "Gold",
        "_neededAmount": 35000000,
        "_currentAmount": 0,
        "_initialAmount": 0
      },
      {
        "_type": "b",
        "_material": "Steel",
        "_neededAmount": 350000,
        "_currentAmount": 0,
        "_initialAmount": 0
      },
      {
        "_type": "b",
        "_material": "U-235",
        "_neededAmount": 75000,
        "_currentAmount": 0,
        "_initialAmount": 0
      },
      {
        "_type": "b",
        "_material": "Rubber",
        "_neededAmount": 60000,
        "_currentAmount": 0,
        "_initialAmount": 0
      },
      {
        "_type": "b",
        "_material": "Wires",
        "_neededAmount": 350000,
        "_currentAmount": 0,
        "_initialAmount": 0
      },
      {
        "_type": "b",
        "_material": "Plastics",
        "_neededAmount": 60000,
        "_currentAmount": 0,
        "_initialAmount": 0
      }
    ],
    "_number": 57,
    "_contractor": "Mizuki",
    "_selected": false,
    "_any": false
  },
  {
    "_objectives": [
      {
        "_type": "b",
        "_material": "Carbon",
        "_neededAmount": 275000,
        "_currentAmount": 0,
        "_initialAmount": 0
      },
      {
        "_type": "b",
        "_material": "Titanium",
        "_neededAmount": 275000,
        "_currentAmount": 0,
        "_initialAmount": 0
      },
      {
        "_type": "b",
        "_material": "Silicon",
        "_neededAmount": 250000,
        "_currentAmount": 0,
        "_initialAmount": 0
      }
    ],
    "_number": 58,
    "_contractor": "Mizuki",
    "_selected": false,
    "_any": false
  },
  {
    "_objectives": [
      {
        "_type": "s",
        "_material": "Wagon",
        "_neededAmount": 650,
        "_currentAmount": 0,
        "_initialAmount": 0
      }
    ],
    "_number": 59,
    "_contractor": "Mizuki",
    "_selected": false,
    "_any": false
  },
  {
    "_objectives": [
      {
        "_type": "s",
        "_material": "TS",
        "_neededAmount": 400,
        "_currentAmount": 0,
        "_initialAmount": 0
      }
    ],
    "_number": 60,
    "_contractor": "Mizuki",
    "_selected": false,
    "_any": false
  }
]